ccontext/Helvetica.ttf
ccontext/NotoEmoji.ttf
ccontext/__init__.py
ccontext/__main__.py
ccontext/argument_parser.py
ccontext/cli.py
ccontext/clipboard.py
ccontext/config.json
ccontext/configurator.py
ccontext/content_handler.py
ccontext/file_node.py
ccontext/file_system.py
ccontext/file_tree.py
ccontext/fix_wsl.py
ccontext/main.py
ccontext/md_generator.py
ccontext/output_handler.py
ccontext/pdf_generator.py
ccontext/research_pdf_generator.py
ccontext/run_crawlers.py
ccontext/tokenizer.py
ccontext/utils.py
ccontext-0.3.9.dist-info/METADATA
ccontext-0.3.9.dist-info/WHEEL
ccontext-0.3.9.dist-info/entry_points.txt
ccontext-0.3.9.dist-info/RECORD
