Metadata-Version: 2.3
Name: ccontext
Version: 0.3.9
Summary: collect-context: Makes the process of collecting and sending context to an LLM like ChatGPT-4o as easy as possible.
License: MIT
Keywords: context,ccontenxt,collect context,llm,chatgpt
Author: Nicolas Arnouts
Author-email: arnouts.software@gmail.com
Requires-Python: >=3.9,<4
Classifier: Development Status :: 3 - Alpha
Classifier: Intended Audience :: Developers
Classifier: License :: OSI Approved :: MIT License
Classifier: Programming Language :: Python :: 3
Classifier: Programming Language :: Python :: 3.9
Classifier: Programming Language :: Python :: 3.10
Classifier: Programming Language :: Python :: 3.11
Classifier: Programming Language :: Python :: 3.12
Classifier: Programming Language :: Python :: 3.13
Classifier: Topic :: Software Development :: Build Tools
Requires-Dist: colorama (==0.4.6)
Requires-Dist: mammoth (>=1.9.0,<2.0.0)
Requires-Dist: pathspec (==0.12.1)
Requires-Dist: pypdf (>=5.8.0,<6.0.0)
Requires-Dist: pyperclip (==1.9.0)
Requires-Dist: reportlab (>=4.4.2,<5.0.0)
Requires-Dist: tiktoken (>=0.9.0,<0.10.0)
Requires-Dist: wcmatch (>=10.1,<11.0)
Project-URL: Documentation, https://github.com/NicolasArnouts/ccontext
Project-URL: Homepage, https://github.com/NicolasArnouts/ccontext
Project-URL: Issues, https://github.com/NicolasArnouts/ccontext/issues
Project-URL: Repository, https://github.com/NicolasArnouts/ccontext
